Metadata-Version: 1.0
Name: distributiongaussian
Version: 1.0
Summary: package of distribution and gausssian py
Home-page: UNKNOWN
Author: UNKNOWN
Author-email: UNKNOWN
License: UNKNOWN
Platform: UNKNOWN
